Workbook

Sheet Read Me
A1: AI Governance Law Matrix — US (Federal & State) and Global
A2: Futran Solutions · AI Task Force · Status as of 5 October 2026
A4: Purpose | B4: One-page reference for which US laws reach AI systems: (1) existing US federal laws that already apply to AI, (2) new AI-specific US state laws by state and regulated feature, and (3) AI governance laws in the EU, UK, Canada, Mexico, Brazil, India, the Gulf, Australia and Singapore.
A5: Tabs | B5: Federal Laws — existing statutes, regulations, executive actions and pending bills, with when each reaches AI and what it requires. State Matrix — 26 of the most active states (rows) × 8 regulated features (columns). Each cell gives the law, effective date and core obligations. Global Matrix — 12 jurisdictions (EU, UK, Canada, Mexico, Brazil, India, UAE, Saudi Arabia, Qatar, Bahrain, Australia, Singapore) × the same features as the State Matrix. EU · UK · Canada · Mexico · Brazil · India · Gulf · Australia · Singapore — one detail tab per jurisdiction in the Federal Laws layout: each law, its type (binding / guidance / voluntary / pending), regulator, when it reaches AI, obligations and 2025–26 dates. Coverage Summary — how many listed states and jurisdictions have an entry in each feature area (live COUNTIF formulas). Sources — where the 2025–26 information came from.
A6: How to read the State Matrix | B6: Columns are the feature of an AI system that triggers the law: making consequential decisions, hiring, profiling personal data, health/insurance use, chatbots and minors, synthetic content and likeness, frontier-model development, and biometrics/neural data/pricing. A final column covers government use, other items and pending bills. '—' means no AI-specific law identified for that state and feature. Federal laws (Federal Laws tab) still apply in every state.
A7: Colour key | B7: Navy header = column / feature. Light blue first column = state. Amber cell = contains a detail marked '(verify)' — status or date not confirmed from a primary source; check before relying on it.
A8: Key takeaway | B8: Most obligations on companies that DEPLOY AI come from (a) existing federal anti-discrimination, consumer-protection, credit and health law, and (b) state laws on how AI is USED — the laws least likely to be displaced by any federal preemption proposal currently under discussion.
A9: Scope limits | B9: Not exhaustive: states enacted 84 AI laws in the first half of 2026 alone. The matrix prioritizes laws that create obligations for businesses. Election-only deepfake laws and narrow public-sector rules are noted selectively. Local laws are included only where significant (NYC Local Law 144).
A10: Disclaimer | B10: For general information only; not legal advice. AI law is changing month to month — confirm current status with counsel before acting.

Sheet Federal Laws
A1: Federal Laws Affecting AI Governance
A2: Existing laws apply to AI today with no AI-specific statute required. Executive actions and voluntary instruments are guidance, not binding law on private companies.
A4: Category | B4: Law / Instrument | C4: Type | D4: Enforcer | E4: When it reaches AI | F4: Key obligations for organizations using AI | G4: 2025–26 developments | H4: Most affected
A5: Employment | B5: Title VII, Civil Rights Act of 1964 | C5: Statute | D5: EEOC; private lawsuits | E5: AI screening, ranking, interviewing or promotion tools that produce disparate impact by race, color, religion, sex or national origin. | F5: Employer liable for discriminatory effect even when the tool is a vendor's. Validate tools, monitor selection rates (4/5ths rule), keep records, offer alternatives. | G5: EEOC removed its AI technical-assistance documents (Jan 2025). EO 14281 (Apr 2025) directs agencies to deprioritize disparate-impact enforcement — private suits are unaffected. Mobley v. Workday: court accepted that an AI vendor can be liable as the employer's agent. | H5: Employers, staffing firms, HR-tech vendors
A6: Employment | B6: Age Discrimination in Employment Act (ADEA) | C6: Statute | D6: EEOC; private lawsuits | E6: AI tools that screen out applicants 40+ (e.g., via graduation dates, years of experience, proxies). | F6: Same disparate-impact discipline as Title VII; audit for age effects. | G6: Mobley v. Workday age claims proceeding as a nationwide collective action (certified 2025); Workday ordered to identify employers using HiredScore features. | H6: Employers, staffing firms
A7: Employment | B7: Americans with Disabilities Act (ADA) | C7: Statute | D7: EEOC; DOJ; private lawsuits | E7: Assessments, video/voice analysis, games or chatbots that screen out people with disabilities or make medical inquiries. | F7: Provide reasonable accommodations and alternative assessments; tell applicants how the tool works; avoid disability-related inquiries. | G7: Disability and proxy-discrimination claims allowed to proceed in Mobley (2026). | H7: Employers; customer-facing AI
A8: Employment / Credit | B8: Fair Credit Reporting Act (FCRA) | C8: Statute | D8: CFPB; FTC; private lawsuits | E8: AI vendors that assemble or score third-party data on candidates, tenants or borrowers may be consumer reporting agencies. | F8: Permissible purpose; certifications; disclosure and written authorization (employment); pre-adverse and adverse action notices; accuracy and dispute rights. | G8: Eightfold AI class action (Jan 2026) alleges an AI hiring platform operated as an unregistered CRA. CFPB withdrew many guidance documents in 2025 — FCRA itself unchanged. | H8: Employers, landlords, lenders, background-check & HR-tech vendors
A9: Credit | B9: Equal Credit Opportunity Act (ECOA) / Regulation B | C9: Statute & regulation | D9: CFPB; FTC; bank regulators | E9: AI or complex models used in credit underwriting, pricing or limits. | F9: No discrimination on protected bases; adverse action notices must give specific, accurate reasons — 'the model said so' is not enough. | G9: CFPB circulars (2022-03, 2023-03) on algorithmic adverse-action reasons; CFPB enforcement scaled back in 2025 (verify current circular status). Statute still privately enforceable. | H9: Lenders, fintechs, auto dealers
A10: Housing | B10: Fair Housing Act | C10: Statute | D10: HUD; DOJ; private lawsuits | E10: Tenant-screening scores, ad targeting and pricing algorithms in housing. | F10: Avoid discriminatory effects; validate screening criteria; consider individual circumstances. | G10: SafeRent Solutions settled a tenant-screening algorithm class action ($2.3M, 2024). HUD's 2024 AI guidance status under current administration uncertain (verify). | H10: Landlords, property managers, screening vendors
A11: Consumer protection | B11: FTC Act §5 (unfair or deceptive practices) | C11: Statute | D11: FTC | E11: False or unsupported AI claims ('AI washing'), unfair AI deployments, misuse of data to train models, deceptive chatbots. | F11: Substantiate AI marketing claims; assess and test for foreseeable harm before deploying; honor privacy promises; avoid dark patterns. | G11: Operation AI Comply (2024); Rite Aid facial-recognition ban (2023); 6(b) study of companion chatbots (Sept 2025); reported investigation of frontier labs over AI safety (2026). AI Action Plan directs review of prior FTC actions that 'unduly burden' AI. | H11: All businesses using or marketing AI
A12: Consumer protection / Minors | B12: Children's Online Privacy Protection Act (COPPA) & 2025 amended Rule | C12: Statute & regulation | D12: FTC; state AGs | E12: AI products or training data involving personal data of children under 13. | F12: Verifiable parental consent; separate consent before disclosing children's data to third parties (including for AI training); data minimization and retention limits. | G12: Amended Rule effective June 2025; compliance deadline 22 April 2026. | H12: Ed-tech, consumer apps, chatbot providers
A13: Content | B13: TAKE IT DOWN Act (2025) | C13: Statute | D13: DOJ (criminal); FTC (platforms) | E13: Publishing non-consensual intimate images, including AI-generated deepfakes. | F13: Covered platforms must run a notice-and-removal process and take down flagged content within 48 hours. | G13: Signed 19 May 2025; platform removal obligations in force since 19 May 2026. | H13: Platforms, generative-image providers
A14: Health | B14: HIPAA Privacy & Security Rules | C14: Statute & regulation | D14: HHS Office for Civil Rights | E14: Any AI tool that creates, receives, stores or transmits protected health information (PHI). | F14: Business associate agreement (BAA) with AI vendors; minimum-necessary use; de-identification before training; security risk analysis covering AI. | G14: Proposed Security Rule update (Jan 2025) would require AI assets in risk analysis and asset inventory (verify final status). | H14: Providers, health plans, health-tech vendors
A15: Health | B15: ACA §1557 Rule — 45 CFR 92.210 | C15: Regulation | D15: HHS Office for Civil Rights | E15: 'Patient care decision support tools,' including AI, used by covered health programs. | F15: Make reasonable efforts to identify tools that use protected characteristics and mitigate discrimination risk. | G15: Obligation effective 1 May 2025. | H15: Hospitals, clinics, health plans
... A30: Pending | B30: Ratepayer Protection Act | C30: Pending bill | D30: — | E30: Data-center energy costs. | F30: Would push states to make data centers pay full grid-upgrade costs. | G30: Passed House 417–3 (Sept 2026); stalled in Senate. | H30: Data-center operators, utilities

Sheet State Matrix
A1: State AI Law Matrix — states × regulated AI features
A2: Each cell: law · effective date · core obligations. '—' = no AI-specific law identified. Amber = contains a '(verify)' item. Federal laws apply in every state in addition.
A4: State | B4: Consequential decisions / ADMT (comprehensive AI laws) | C4: Employment & hiring AI | D4: Privacy law — profiling & automated-decision rights | E4: Health care & insurance AI | F4: Chatbots, companions & minors | G4: Synthetic content, deepfakes & likeness | H4: Frontier model safety | I4: Biometrics, neural data & algorithmic pricing | J4: Government use · other · pending / key dates
A5: California | B5: No single comprehensive AI act. CCPA automated-decisionmaking technology (ADMT) regulations (CPPA, finalized 2025): pre-use notice, opt-out and access rights where ADMT makes significant decisions; risk assessments; ADMT compliance from 1 Jan 2027. 2026: SB 813 creates an Independent Verification Organization (IVO) framework for AI systems; AB 1405 creates an AI auditor registry (registration from 2029). | C5: FEHA automated-decision system regulations (eff. 1 Oct 2025): ADS-driven discrimination is unlawful; anti-bias testing relevant to defenses; 4-year record retention; vendors can be agents. SB 947 'No Robo Bosses Act of 2026' (signed Sept 2026; effective date verify): employers may not rely solely on an ADS for discipline or termination; human review before adverse action. CCPA ADMT rules also cover employment decisions. | D5: CCPA/CPRA: right to opt out of and access information about ADMT; risk assessments for significant decisions (2027). SB 923 (2026) expands deletion rights to data collected 'from or about' consumers. | E5: SB 1120 (2025): medical-necessity denials must be made by a licensed clinician, not AI alone. AB 3030 (2025): disclaimer on generative-AI patient communications. AB 489 (2025): AI may not imply it is a licensed health professional. AB 1979 (2026): AI may not independently perform functions reserved to licensed clinicians. Vetoed 2026: SB 903 (AI psychotherapy), AB 2575. | F5: SB 243 (eff. 1 Jan 2026): companion chatbots must disclose they are AI, run self-harm/988 protocols, protect minors, report annually; private right of action. SB 1119 'Adam's Law' (signed 12 Sept 2026): stronger protections for minors — age verification, parental controls, in-app crisis support, audits. AB 1709 (2026): bans addictive features for under-16s; AB 2246 replaces the Age-Appropriate Design Code. | G5: AI Transparency Act (SB 942) amended by SB 1000 (2026): latent disclosures in AI content; 1M-user threshold removed. AB 2013 (eff. 1 Jan 2026): developers publish training-data summaries. SB 1050 (2026): disclose AI 'synthetic performers' in ads; SB 1111: digital-replica likeness rights; AB 2025: disclose AI-altered real-estate images. Election deepfake laws AB 2655/AB 2839 largely struck down in court (2025). | H5: SB 53 Transparency in Frontier AI Act (eff. 1 Jan 2026): developers training >10^26 FLOP; 'large' developers (>$500M revenue) publish a frontier AI framework and transparency reports, report critical safety incidents to Cal OES within 15 days; whistleblower protections; penalties up to $1M. | I5: CCPA treats neural data as sensitive personal information (SB 1223, 2024). AB 1883 (workplace AI collecting neural data / recognizing emotion) sent to the Governor in 2026 — outcome (verify). | J5: Key dates: SB 53, SB 243, AB 2013 in force since 1 Jan 2026; CCPA ADMT obligations 1 Jan 2027. 2026 session: 22 privacy/AI bills signed, 3 vetoed.
A6: Colorado | B6: SB 26-189 (signed 14 May 2026; compliance 1 Jan 2027) repeals and replaces the 2024 Colorado AI Act (SB 24-205). Covers ADMT that materially influences consequential decisions in employment, housing, credit, insurance, health care, education and government services. Developers: documentation to deployers (uses, risks, data categories), 3-year retention. Deployers: notice before use; plain-language explanation within 30 days of an adverse outcome; right to correct data; human review/reconsideration where commercially reasonable. Removed: risk-management program, impact assessments, duty of reasonable care. AG-only enforcement; 60-day cure until 2030; no private right of action. AG rules due 1 Jan 2027. xAI v. Weiser challenge stayed. | C6: Employment is a covered consequential decision under SB 26-189 (notice, adverse-decision explanation, correction, human review). HB 26-1210 also restricts algorithmic wage-setting (see pricing column). | D6: Colorado Privacy Act: opt-out of profiling for decisions with legal or similarly significant effects; data protection assessments; biological/neural data are sensitive data (HB 24-1058). | E6: SB 21-169: insurers may not use external consumer data or algorithms that unfairly discriminate; Division of Insurance governance and testing rules (life insurance first). HB 26-1139 (2026): AI utilization review must rest on individual clinical history; periodic accuracy audits; no denial based solely on AI; no coverage of AI-delivered psychotherapy. | F6: HB 26-1263 (eff. 1 Jan 2027): companion chatbots must detect crisis indicators and redirect to emergency resources; periodic AI reminders. | G6: HB 24-1147: disclosure required on AI deepfakes of candidates near elections. | H6: — | I6: HB 26-1210: bans surveillance (personal-data-based individual) pricing and certain algorithmic wage-setting; AG rulemaking; private right of action. | J6: Key date: 1 Jan 2027 — SB 26-189 and HB 26-1263 obligations begin.
A7: Connecticut | B7: SB 5 (2026) — CT AI Responsibility and Transparency Act (signed May 2026; phases in Oct 2026–Jan 2028). Most violations are unfair trade practices enforced by the AG. | C7: SB 5: from 1 Oct 2027 developers must inform deployers about employment decision tools, and employers must tell applicants/employees the tool's purpose, trade name, data sources and assessment methods; use of a tool is no defense to discrimination (anti-bias testing may be considered). From 1 Oct 2026: mass-layoff/plant-closing notices must state whether layoffs relate to AI use. | D7: CT Data Privacy Act: profiling opt-out; data protection assessments. 2025 amendments add rights around profiling decisions and impact assessments (eff. 1 July 2026) (verify details). | E7: — | F7: SB 5: companion chatbots must disclose they are not human (hourly for minors, every 3 hours for adults); for minors, must not encourage eating disorders, violence, romantic interaction or manipulative engagement. | G7: SB 5: providers with >1M monthly users must embed tamper-resistant provenance data in AI-generated or materially altered content (from 1 Oct 2026). | H7: SB 5: large frontier developers must set up anonymous internal whistleblower channels by 1 Jan 2027. | I7: SB 4 (2026): bans customized prices for a specific consumer based on personal data; AG-only enforcement. | J7: Key dates: 1 Oct 2026 (layoff AI disclosure, provenance), 1 Jan 2027 (whistleblower), 1 Oct 2027 (employment tool notices).
A8: Illinois | B8: — | C8: HB 3773, amending the Illinois Human Rights Act (eff. 1 Jan 2026): discriminatory AI use in recruitment, hiring, promotion, discipline or discharge is a civil-rights violation; zip codes may not be used as a proxy; employers must notify employees of AI use. AI Video Interview Act (2020): notice, explanation and consent before AI analysis of video interviews; deletion on request; demographic reporting if AI alone decides who gets an in-person interview. | D8: — | E8: WOPR Act, HB 1806 (Aug 2025): bans AI from providing therapy or making therapeutic decisions; licensed professionals may use AI for administrative support; penalties up to $10,000. SB 3114 (2026): human review required for every algorithmic claim-downcoding decision. | F8: — | G8: Digital replica and right-of-publicity amendments (2024) restrict unauthorized AI replicas of voice and likeness; civil remedy for sexual deepfakes (verify bill numbers). | H8: SB 315 AI Safety Measures Act (signed 6 July 2026; key obligations 1 Jan 2028): developers >10^26 FLOP whose models reach Illinois users; large developers (>$500M revenue) publish safety frameworks, undergo ANNUAL THIRD-PARTY AUDITS (first state), report critical incidents within 72 hours (24 if imminent risk of death or injury); transparency reports; whistleblower protections; AG civil penalties. | I8: Biometric Information Privacy Act (BIPA): written notice and consent before collecting face, voice or fingerprint data; retention policy; private right of action (2024 amendment limits damages to one recovery per person). | J8: Key dates: HB 3773 in force since 1 Jan 2026; SB 315 audits from 2028.
A9: New York (incl. NYC) | B9: — | C9: NYC Local Law 144 (enforced since July 2023): automated employment decision tools need an independent bias audit within the past year, a published summary and 10 business days' notice to NYC candidates; DCWP fines $500–$1,500 per violation per day. A Dec 2025 State Comptroller audit found enforcement weak; DCWP committed to stronger enforcement. State bill A 9581 (AI hiring impact reporting by large employers) passed both chambers in 2026, not yet signed (verify). | D9: No comprehensive state privacy law. Algorithmic Pricing Disclosure Act (eff. Nov 2025): prices set by an algorithm using personal data must carry a disclosure. | E9: — | F9: General Business Law Art. 47 (eff. 5 Nov 2025): companion chatbots must disclose they are AI and run self-harm/crisis protocols; AG penalties up to $15,000 per day. | G9: Synthetic-performer disclosure in ads (signed Dec 2025) (verify effective date); election deepfake disclosure law (2024). | H9: RAISE Act (signed Dec 2025, amended 2026; eff. 1 Jan 2027): large frontier developers (>$500M revenue, >10^26 FLOP) publish a frontier AI framework and transparency reports; report critical incidents within 72 hours to a new office in the Dept. of Financial Services; AG penalties up to $1M (first) and $3M (subsequent). | I9: NYC biometric identifier law (2021): commercial establishments must post signs and may not sell biometric data. | J9: LOADinG Act (2024): state agencies must inventory automated decision systems and keep human review. Pending: data-center moratorium bill (S10642).
A10: Texas | B10: TRAIGA, HB 149 (eff. 1 Jan 2026): applies to anyone doing business in Texas. Bans developing or deploying AI with INTENT to manipulate people toward self-harm, harm or crime; unlawfully discriminate (disparate impact alone is not enough); produce CSAM or illegal deepfakes; infringe constitutional rights. AG-only enforcement; 60-day cure; $10k–$12k (curable), $80k–$200k (uncurable), $2k–$40k per day (continuing). Affirmative defense for substantial compliance with NIST AI RMF plus internal testing. 36-month regulatory sandbox; AI Council. | C10: Only through TRAIGA's intent-based discrimination ban — no hiring-specific AI law. | D10: Texas Data Privacy and Security Act (2024): profiling opt-out; data protection assessments. | E10: TRAIGA: health-care providers must disclose AI use in patient care. SB 1188 (2025): practitioners using AI for diagnosis must review records and disclose (verify details). | F10: — | G10: Election deepfake crime (2019); sexual deepfake offenses expanded 2023/2025. | H10: — | I10: Capture or Use of Biometric Identifiers Act (CUBI): consent before capturing biometrics; AG enforcement (Meta $1.4B settlement 2024; Google $1.375B 2025). | J10: TRAIGA government rules: agencies must disclose AI interactions, may not use social scoring, need consent for biometric identification.
A11: Utah | B11: Artificial Intelligence Policy Act (2024; amended 2025 by SB 226 and SB 332; sunset extended to July 2027): disclose generative AI when a consumer clearly asks; regulated occupations must proactively disclose in 'high-risk' interactions. Office of AI Policy runs a learning lab with regulatory mitigation agreements. | C11: — | D11: Utah Consumer Privacy Act: no profiling opt-out. | E11: HB 452 (May 2025): mental-health chatbots must disclose AI at access, every 7 days and on request; no sale of individual health data or targeted ads; fines up to $2,500. SB 319 (2026): public reporting of prior-authorization statistics and AI use; independent medical judgment for adverse determinations. | F11: HB 452 mental-health chatbot rules (see health column). | G11: SB 271 (2025): bans unauthorized AI simulations of a person's likeness or voice in commerce and fundraising, and tools primarily designed for that purpose. | H11: — | I11: — | J11: Key date: AI Policy Act sunset July 2027 unless extended.
A12: Maryland | B12: — | C12: HB 1202 (2020): applicant consent required before facial recognition is used in job interviews. | D12: Maryland Online Data Privacy Act (eff. 1 Oct 2025): strict data-minimization; ban on selling sensitive data; profiling opt-out; assessments. | E12: — | F12: — | G12: — | H12: — | I12: HB 895 Protection From Predatory Pricing Act (eff. 1 Oct 2026): bans using personal data to set higher individualized prices; AG-only enforcement. | J12: State agencies must inventory high-risk AI (2024 law).
A13: New Jersey | B13: — | C13: No AI-specific hiring statute enacted. NJ Division on Civil Rights guidance (Jan 2025): the Law Against Discrimination covers algorithmic discrimination, including disparate impact, and employers are liable for vendor tools. Pending 2026 bills on automated employment decision tools (e.g., S4075, A2726). | D13: NJ Data Privacy Act (eff. Jan 2025): profiling opt-out; data protection assessments; Division of Consumer Affairs rules. | E13: — | F13: Pending chatbot / frontier proposals in 2026. | G13: Deceptive deepfake law (Apr 2025): civil and criminal penalties for harmful AI-generated media. | H13: — | I13: — | J13: —
A14: Virginia | B14: HB 2094 high-risk AI act vetoed (2025). SB 384 / HB 797 (signed 13 Apr 2026): directs the Joint Commission on Technology and Science to study an Independent Verification Organization framework for AI. | C14: — | D14: Virginia Consumer Data Protection Act: profiling opt-out; data protection assessments. | E14: — | F14: — | G14: — | H14: — | I14: — | J14: Executive Order 22 (Sept 2026): data-center accountability framework and a new state AI task force.
A15: Washington | B15: — | C15: — | D15: No comprehensive privacy law. My Health My Data Act (2024): consent for consumer health data (incl. biometric); private right of action. | E15: SB 5395: only licensed professionals may deny care; AI cannot be the sole basis to deny, delay or modify care. | F15: HB 2225 (eff. 1 Jan 2027): periodic AI-interaction reminders, protections for minors, parental controls. | G15: Election deepfake disclosure (2023); forged digital likeness offenses (2025) (verify). | H15: — | I15: Biometric identifier law (RCW 19.375): notice and consent for commercial biometric enrollment. | J15: State AI Task Force reports to the Legislature.
... A30: Massachusetts | B30: No AI statute. Attorney General advisory (Apr 2024): existing consumer protection, anti-discrimination and data security laws apply to AI developers and users. | C30: — | D30: — | E30: — | F30: Frontier and chatbot proposals under consideration (2026). | G30: — | H30: Frontier proposals pending (2026). | I30: — | J30: —

Sheet Global Matrix
A1: Global AI Law Matrix — jurisdictions × regulated AI features
A2: Same features as the State Matrix. '—' = no AI-specific rule identified. Amber = contains a '(verify)' item. Detail for each jurisdiction is on its own tab.
A4: Jurisdiction | B4: Comprehensive AI law / consequential decisions | C4: Employment & hiring AI | D4: Privacy law — automated-decision rights | E4: Health care & insurance AI | F4: Chatbots, companions & minors | G4: Synthetic content, deepfakes & likeness | H4: Frontier / general-purpose model rules | I4: Biometrics & surveillance | J4: Regulators · key dates · pending
A5: European Union | B5: EU AI Act (in force Aug 2024): risk-based, binding; fines up to €35M/7%. High-risk duties deferred by Digital Omnibus to 2 Dec 2027 (Annex III) and 2 Aug 2028 (Annex I). | C5: Hiring, promotion, task allocation, monitoring and termination AI is HIGH-RISK (Annex III) from 2 Dec 2027: deployer human oversight, logging, worker notice. Platform Work Directive (Dec 2026) adds algorithmic-management rights. | D5: GDPR Art. 22: right not to be subject to solely automated significant decisions; human intervention, contestation, explanation of logic (CJEU 2023, 2025). | E5: Life and health insurance pricing and access to essential health services are high-risk; AI medical devices under MDR/IVDR (Annex I, Aug 2028). | F5: Art. 50: chatbots must disclose AI (from 2 Aug 2026). DSA protections for minors on platforms. | G5: Art. 50 machine-readable marking and deepfake disclosure (Aug 2026); new ban on AI-generated CSAM and non-consensual intimate imagery (Omnibus 2026). | H5: GPAI obligations since 2 Aug 2025 (documentation, copyright policy, training-data summary); systemic-risk models: evaluations, incident reporting, cybersecurity. Code of Practice July 2025. | I5: Bans (since Feb 2025): untargeted facial-image scraping, emotion recognition at work and school, social scoring, most real-time remote biometric ID by police. | J5: AI Office + national authorities. Product Liability Directive covers AI software from 9 Dec 2026.
A6: United Kingdom | B6: No AI Act; principles applied by sector regulators. AI Growth Lab sandboxes (June 2026). | C6: Equality Act 2010 liability for discriminatory AI; DUAA safeguards apply to automated hiring decisions. | D6: UK GDPR Arts. 22A–D (DUAA s.80, from 5 Feb 2026): automated decisions allowed on any lawful basis with safeguards — information, representations, human intervention, contestation. | E6: MHRA rules for AI as a medical device; FCA Consumer Duty for insurance. | F6: Online Safety Act: Ofcom child-safety duties cover AI chatbots in scope. | G6: Criminal offences for sharing and creating sexual deepfakes. | H6: AI Security Institute (voluntary pre-deployment testing); no binding frontier rules. | I6: ICO guidance on biometric recognition; UK GDPR special-category rules. | J6: ICO AI code of practice duty in force May 2026 (code pending). Copyright & AI policy pending.
A7: Canada | B7: No federal AI act (AIDA died 2025). Bill C-36 (tabled June 2026) would add automated-decision transparency. | C7: Ontario: disclose AI screening in job postings (from 1 Jan 2026). Human-rights codes apply. | D7: Quebec Law 25 s.12.1: notice of exclusively automated decisions, reasons, correction and human review. PIPEDA principles. | E7: — | F7: Online Harms Act died 2025; no chatbot-specific law. | G7: Criminal Code covers non-consensual intimate images; no AI-labelling law. | H7: Voluntary Code of Conduct on Advanced Generative AI (2023); Canadian AI Safety Institute. | I7: OPC guidance on biometrics; Quebec biometric database disclosure rules. | J7: Federal Directive on Automated Decision-Making for government.
A8: Mexico | B8: No general AI law; 80+ pending initiatives; constitutional reform needed first. | C8: Federal Labour Law platform-work reform: algorithmic transparency for platform workers. | D8: New LFPDPPP (Mar 2025): privacy rights incl. automated processing (verify scope); enforcement moved from INAI to the executive. | E8: — | F8: Presidential forums on AI and minors (Aug–Sept 2026) — initiative expected. | G8: Copyright reform (May 2026): consent to AI-clone a performer's voice or image. State 'Ley Olimpia' deepfake offences. | H8: — | I8: — | J8: Watch: Senate AI commission; USMCA review.
A9: Brazil | B9: PL 2338/2023 passed Senate Dec 2024; stalled in Chamber of Deputies. | C9: LGPD Art. 20 review right covers automated hiring decisions; no hiring-specific AI law. | D9: LGPD Art. 20: right to review solely automated decisions and receive criteria information. | E9: — | F9: ECA Digital (Lei 15.211/2025, in force Mar 2026): child safety by default, age verification, parental controls. | G9: TSE Res. 23.755/2026: AI labels on campaign content; electoral deepfakes banned; 72-hour blackout before votes. | H9: Proposed in PL 2338 (general-purpose model duties). | I9: LGPD sensitive-data rules for biometrics. | J9: ANPD is the lead digital regulator. Elections 4 Oct 2026 (runoff 25 Oct).
A10: India | B10: No AI law; voluntary India AI Governance Guidelines (Nov 2025). | C10: No AI-specific employment rules. | D10: DPDP Act + Rules (Nov 2025; fully applicable 13 May 2027): consent, purpose limits, DPIAs and algorithmic due diligence for Significant Data Fiduciaries; no explicit automated-decision right. | E10: ICMR ethical guidelines for AI in health (2023). | F10: DPDP: verifiable parental consent; no tracking or targeted ads to children. | G10: IT Rules amendment (in force 20 Feb 2026): mandatory labels and provenance metadata for AI content; 3-hour takedowns; detection for large platforms. | H10: — | I10: DPDP covers biometric data as personal data. | J10: RBI FREE-AI (Aug 2025) for financial sector; Data Protection Board.
A11: UAE | B11: No AI statute. UAE AI Charter (2024); new Federal Authority for AI and Data (June 2026). | C11: — | D11: PDPL: right to object to automated processing with legal effects. DIFC Regulation 10 for autonomous systems. | E11: — | F11: — | G11: Cybercrime law penalizes fabricated content and rumours, including deepfakes. | H11: — | I11: — | J11: CBUAE AI/ML guidance (Feb 2026): annual bias testing, human review, kill switch.
A12: Saudi Arabia | B12: No AI statute. SDAIA ethics principles and National AI Risk Management Framework (July 2026). | C12: — | D12: PDPL (enforced Sept 2024): data-subject rights, transfer limits, DPIAs; fines up to SAR 5M. | E12: — | F12: — | G12: SDAIA deepfake guidelines (non-binding); anti-cybercrime law. | H12: Generative AI guidelines (non-binding). | I12: — | J12: Copyright TDM exception from 12 Aug 2026; draft Global AI Hub Law.
A13: Qatar | B13: No AI statute; MCIT ethical AI guidelines (2025). | C13: — | D13: PDPPL (Law 13/2016). | E13: — | F13: — | G13: — | H13: — | I13: — | J13: QCB AI Guidelines (Sept 2024) — binding for licensed financial institutions.
A14: Bahrain | B14: 38-article AI law proposed (criminal penalties); not enacted as of July 2026. | C14: — | D14: PDPL (Law 30/2018). | E14: — | F14: — | G14: — | H14: — | I14: — | J14: Government AI policy mandatory for public bodies (May 2025).
A15: Australia | B15: No AI act; National AI Plan (Dec 2025) relies on existing law; Office of AI developing standards (July 2026). | C15: Fair Work and anti-discrimination laws apply; no AI-specific hiring law. | D15: Privacy Act: disclose automated decisions in privacy policies from 10 Dec 2026; statutory privacy tort (June 2025). | E15: TGA regulates AI as a medical device. | F15: Under-16 social-media minimum age (Dec 2025); eSafety codes cover AI companions. | G15: Deepfake Sexual Material Act 2024 (criminal). | H15: AI Safety Institute (testing; non-binding). | I15: OAIC determinations against facial-recognition misuse (e.g., Bunnings 2024). | J15: OAIC, ACCC, ASIC, eSafety share oversight. TDM exception ruled out (Oct 2025).
A16: Singapore | B16: No AI act; voluntary Model AI Governance Frameworks incl. Agentic AI (Jan 2026); AI Verify. | C16: Workplace Fairness Act 2025 (commencement 2026–27, verify) covers AI-assisted decisions. | D16: PDPA + Advisory Guidelines on AI recommendation and decision systems (2024). | E16: MOH AI in Healthcare Guidelines; HSA medical-device rules. | F16: — | G16: Election deepfake ban (2024); Online Safety (Relief and Accountability) Act 2025. | H16: — | I16: — | J16: MAS AI Risk Management Guidelines (consulted 2025–26). Copyright exception allows AI training.

Sheet EU
A1: European Union — AI Governance Laws
A2: The EU has the world's only horizontal AI statute (AI Act), layered on GDPR and product, platform and consumer law. Applies to non-EU companies whose AI is placed on the EU market or whose outputs are used in the EU.
A4: Category | B4: Law / Instrument | C4: Type | D4: Regulator / Enforcer | E4: When it reaches AI | F4: Key obligations for organizations using AI | G4: 2025–26 developments & key dates | H4: Most affected
A5: Comprehensive AI law | B5: EU AI Act — Regulation (EU) 2024/1689 | C5: Binding regulation | D5: EU AI Office (GPAI); national market-surveillance authorities | E5: Any AI system placed on the EU market or whose output is used in the EU — providers, deployers, importers, distributors. | F5: Risk tiers: (1) prohibited practices; (2) high-risk systems (Annex III: employment, credit scoring, life/health insurance pricing, education, essential services, biometrics, law enforcement) — risk management, data governance, technical documentation, logging, human oversight, accuracy, conformity assessment, registration; deployers must follow instructions, assign human oversight, keep logs, inform workers and affected people, and (public bodies, credit, insurance) run fundamental-rights impact assessments; (3) transparency duties; (4) general-purpose AI model duties. Fines up to €35M or 7% of global turnover. | G5: Prohibitions and AI literacy since 2 Feb 2025. GPAI model obligations since 2 Aug 2025; Commission enforcement powers over GPAI from 2 Aug 2026. Article 50 transparency since 2 Aug 2026. | H5: Every company selling or using AI in the EU
A6: Comprehensive AI law | B6: Digital Omnibus on AI — Regulation (EU) 2026/1744 | C6: Binding amending regulation | D6: European Commission | E6: Amends AI Act timelines and scope. | F6: High-risk obligations deferred: Annex III stand-alone systems to 2 Dec 2027; Annex I product-embedded systems to 2 Aug 2028. New prohibition on AI generating CSAM and non-consensual intimate imagery. Watermarking grace period to 2 Dec 2026 for systems already on the market. Lighter documentation and penalties for SMEs and small mid-caps; AI-literacy duty softened to 'supporting' staff competence. | G6: Published OJ 24 July 2026; in force 27 July 2026. | H6: High-risk AI providers and deployers
A7: Transparency / synthetic content | B7: AI Act Article 50 & GPAI Code of Practice | C7: Binding (Art. 50); voluntary code | D7: AI Office; national authorities | E7: Chatbots, emotion recognition, biometric categorization, and AI-generated or manipulated content (deepfakes). | F7: Tell people they are interacting with AI; machine-readable marking of AI-generated content; disclose deepfakes and AI-generated public-interest text. GPAI providers: technical documentation, copyright policy, training-data summary; systemic-risk models add evaluations, incident reporting, cybersecurity. | G7: Art. 50 applies from 2 Aug 2026. Code of Practice published July 2025 and signed by most major labs. | H7: Chatbot operators, content platforms, model developers
A8: Privacy / automated decisions | B8: GDPR — Art. 22 and Arts. 13–15, 35 | C8: Binding regulation | D8: National data protection authorities; EDPB | E8: Solely automated decisions with legal or similarly significant effects; any AI processing personal data, including training. | F8: Lawful basis for training and use; right not to be subject to solely automated decisions (with exceptions) plus human intervention, contestation and meaningful information about the logic; DPIAs for high-risk processing; data minimization. Fines up to €20M or 4%. | G8: CJEU SCHUFA (2023): credit scores that strongly drive decisions can be 'automated decisions'. CJEU Dun & Bradstreet Austria (Feb 2025): right to an intelligible explanation of the logic. Italy fined OpenAI €15M (Dec 2024). Commission's Nov 2025 Digital Omnibus proposes GDPR changes for AI training (legislative status: verify). | H8: All controllers using AI on personal data
A9: Employment | B9: Platform Work Directive — (EU) 2024/2831 | C9: Binding directive (national transposition) | D9: National labour authorities | E9: Algorithmic management of platform workers (allocation, pay, deactivation). | F9: Transparency about automated monitoring and decision systems; human review of significant decisions; ban on processing emotional state or private conversations; consultation of worker representatives. | G9: Member-state transposition deadline 2 Dec 2026. | H9: Gig and platform companies
A10: Liability | B10: Product Liability Directive — (EU) 2024/2853 | C10: Binding directive | D10: National courts | E10: Software, including AI systems, treated as a 'product'. | F10: No-fault liability for defective AI software causing harm; disclosure-of-evidence rules and presumptions ease claimants' burden; updates and learning after release count. | G10: Applies to products placed on the market after 9 Dec 2026. The separate AI Liability Directive was withdrawn (2025). | H10: AI developers and integrators
A11: Platforms / minors | B11: Digital Services Act (DSA) | C11: Binding regulation | D11: European Commission (very large platforms); national digital services coordinators | E11: Recommender systems, AI-generated content and generative AI on online platforms. | F11: Recommender transparency and a non-profiling option for very large platforms; systemic-risk assessments (including generative AI); protections for minors; deepfake labelling as a risk mitigation. | G11: Commission guidelines on protecting minors (July 2025); ongoing proceedings against major platforms. | H11: Online platforms, search engines
A12: Data | B12: Data Act — (EU) 2023/2854 | C12: Binding regulation | D12: National authorities | E12: Data from connected products and cloud switching relevant to AI training and services. | F12: User access to and sharing of product data; fair contract terms; cloud-switching rights. | G12: Applies from 12 Sept 2025. | H12: IoT, cloud and data-driven AI businesses
A13: Financial / sectoral | B13: DORA, Consumer Credit Directive 2023, MDR/IVDR | C13: Binding sectoral law | D13: Financial and medical-device regulators | E13: AI in financial operations, credit decisions and medical devices. | F13: ICT risk and third-party oversight (DORA, since Jan 2025); right to human assessment and explanation in automated creditworthiness decisions (CCD 2023, applies Nov 2026); conformity assessment for AI medical devices. | G13: CCD transposition by 20 Nov 2025, application 20 Nov 2026. | H13: Banks, lenders, insurers, med-tech

Sheet UK
A1: United Kingdom — AI Governance Laws
A2: No UK AI Act. The UK regulates AI through existing law and sector regulators under a 'pro-innovation' approach. UK companies serving EU markets are also caught by the EU AI Act.
A4: Category | B4: Law / Instrument | C4: Type | D4: Regulator / Enforcer | E4: When it reaches AI | F4: Key obligations for organizations using AI | G4: 2025–26 developments & key dates | H4: Most affected
A5: Comprehensive AI law | B5: No AI Act — principles-based approach | C5: Policy | D5: Sector regulators (ICO, FCA, CMA, Ofcom, MHRA, EHRC) | E5: All AI, via each regulator's existing remit. | F5: Five cross-sector principles: safety, transparency, fairness, accountability, contestability — applied by regulators, not a statute. | G5: No AI bill introduced as of Oct 2026. AI Growth Lab sandboxes launched 8 June 2026. AI Safety Institute renamed AI Security Institute (2025). | H5: All
A6: Privacy / automated decisions | B6: UK GDPR as amended by Data (Use and Access) Act 2025, s.80 (Arts. 22A–22D) | C6: Binding statute | D6: Information Commissioner's Office (ICO) | E6: Significant decisions based solely on automated processing. | F6: Automated decisions now permitted on any lawful basis (including legitimate interests) IF safeguards: tell people about the decision, let them make representations, get genuine human intervention and contest it. Stricter rules remain for special-category data. | G6: s.80 in force 5 Feb 2026. ICO draft ADM guidance consulted Mar–May 2026; statutory duty to produce an AI code of practice in force 12 May 2026 (code not yet published). | H6: Employers, lenders, insurers, any ADM user
A7: Employment / discrimination | B7: Equality Act 2010 | C7: Binding statute | D7: Employment tribunals; EHRC | E7: AI in recruitment, performance, pay or dismissal causing direct or indirect discrimination. | F7: Employer liable for discriminatory outcomes of AI tools, including vendors'; reasonable adjustments for disabled candidates. | G7: Employment Rights Act 2025 adds wider worker protections (no AI-specific rule). | H7: Employers, recruiters
A8: Online safety / minors | B8: Online Safety Act 2023 | C8: Binding statute | D8: Ofcom | E8: AI chatbots and generative AI in user-to-user or search services; AI-generated illegal content. | F8: Illegal-content and child-safety duties, risk assessments, age assurance for harmful content. | G8: Ofcom enforcing since 2025 and investigating AI chatbots (2026). | H8: Platforms, chatbot providers
A9: Deepfakes | B9: Sexual deepfake offences (Online Safety Act 2023; Data (Use and Access) Act 2025) | C9: Binding statute | D9: Police / CPS | E9: Sharing — and creating — sexually explicit deepfakes without consent. | F9: Criminal liability for sharing (OSA) and for creating (DUAA) intimate deepfakes (verify commencement). | G9: Creation offence added 2025. | H9: Image-generation services, platforms
A10: Financial services | B10: FCA Consumer Duty & SM&CR | C10: Binding regulation | D10: FCA; PRA | E10: AI in financial products, advice, pricing, credit and fraud. | F10: Good outcomes for retail customers; fair value; senior-manager accountability for AI; model risk (PRA SS1/23 for banks). | G10: FCA AI Live Testing service (2025–26); no AI-specific rules planned. | H10: Banks, insurers, fintechs
A11: Competition / consumer | B11: Digital Markets, Competition and Consumers Act 2024 | C11: Binding statute | D11: CMA | E11: Large tech firms' AI ecosystems; misleading AI claims to consumers. | F11: Strategic-market-status conduct requirements; direct CMA fines for consumer-law breaches (fake reviews, drip pricing, misleading claims). | G11: CMA consumer enforcement powers active since Apr 2025. | H11: Big tech; consumer-facing AI
A12: Copyright | B12: Copyright, Designs and Patents Act 1988 | C12: Binding statute | D12: Courts; IPO | E12: Training on copyrighted works; computer-generated works. | F12: Only a non-commercial TDM exception; commercial training needs licences. | G12: Government consultation on an opt-out TDM exception (Dec 2024); DUAA requires reports on AI and copyright — final policy pending (verify). | H12: Model developers, media

Sheet Canada
A1: Canada — AI Governance Laws
A2: No federal AI statute (AIDA died in Jan 2025). AI is governed by privacy law, provincial rules and human-rights law; a new federal privacy bill with automated-decision transparency is before Parliament.
A4: Category | B4: Law / Instrument | C4: Type | D4: Regulator / Enforcer | E4: When it reaches AI | F4: Key obligations for organizations using AI | G4: 2025–26 developments & key dates | H4: Most affected
A5: Comprehensive AI law | B5: Artificial Intelligence and Data Act (AIDA, Bill C-27) | C5: Died on order paper | D5: — | E5: — | F5: None — no federal AI act in force. | G5: Died Jan 2025 when Parliament was prorogued. Minister of AI and Digital Innovation appointed May 2025; Canadian AI Safety Institute (2024). | H5: —
A6: Privacy / automated decisions | B6: Bill C-36 — Protecting Privacy and Consumer Data Act | C6: Pending bill | D6: Proposed Digital Safety and Data Protection Commission | E6: Automated decision systems making significant decisions about individuals; children's data. | F6: Transparency and plain-language explanations of automated decisions; higher standards for children's data; deletion and mobility rights; penalties up to C$10M/3% (C$25M/5% for offences). | G6: Tabled 15 June 2026; not yet law. | H6: All private-sector organizations
A7: Privacy | B7: PIPEDA (federal private-sector privacy law) | C7: Binding statute | D7: Office of the Privacy Commissioner | E7: AI processing personal information in commercial activity. | F7: Consent, purpose limitation, openness, accuracy, access; OPC principles for responsible generative AI (Dec 2023). | G7: Joint OPC investigation of OpenAI ongoing. | H7: All private-sector organizations
A8: Privacy / automated decisions (Quebec) | B8: Quebec Law 25 — Private Sector Act s.12.1 | C8: Binding statute | D8: Commission d'accès à l'information | E8: Decisions based exclusively on automated processing of personal information. | F8: Notify the person; on request disclose the personal information used, reasons and principal factors; right to correct data and to have the decision reviewed by a person. Privacy impact assessments; penalties up to C$25M or 4%. | G8: In force since Sept 2023. | H8: Any business with Quebec customers or staff
A9: Employment (Ontario) | B9: Employment Standards Act — Working for Workers Four Act, 2024 | C9: Binding statute | D9: Ontario Ministry of Labour | E9: Publicly advertised job postings where AI screens, assesses or selects applicants. | F9: Disclose AI use in the job posting; written electronic-monitoring policy for employers with 25+ employees. | G9: In force 1 Jan 2026. Nova Scotia (Bill 234) proposing similar rules. | H9: Employers hiring in Ontario
A10: Employment / discrimination | B10: Canadian Human Rights Act & provincial human-rights codes | C10: Binding statute | D10: Human-rights commissions and tribunals | E10: Discriminatory AI outcomes in employment, housing and services. | F10: Employer and service-provider liability for adverse-effect discrimination; duty to accommodate. | G10: — | H10: Employers, landlords, service providers
A11: Public sector | B11: Treasury Board Directive on Automated Decision-Making; Ontario Bill 194 (2024); Manitoba Bill 51 | C11: Binding on government | D11: Treasury Board; provinces | E11: Federal and provincial government use of AI. | F11: Algorithmic impact assessments, notice, human review, peer review for higher-risk systems. | G11: Directive updated 2025; provinces adding public-sector AI rules. | H11: Government vendors
A12: Voluntary | B12: Voluntary Code of Conduct on Advanced Generative AI Systems | C12: Voluntary | D12: ISED | E12: Developers and managers of generative AI. | F12: Accountability, safety, fairness, transparency, human oversight, robustness commitments. | G12: Launched Sept 2023; 40+ signatories. | H12: GenAI developers

Sheet Mexico
A1: Mexico — AI Governance Laws
A2: No general AI law. Congress has 80+ pending AI initiatives; regulation is moving sector by sector.
A4: Category | B4: Law / Instrument | C4: Type | D4: Regulator / Enforcer | E4: When it reaches AI | F4: Key obligations for organizations using AI | G4: 2025–26 developments & key dates | H4: Most affected
A5: Comprehensive AI law | B5: General Law to Regulate and Foster AI (proposals) | C5: Pending | D5: Senate special commission | E5: — | F5: Proposals include risk tiers, bans on cognitive manipulation and a National AI Agency with fining powers. | G5: Not advanced to the Senate floor by the end of ordinary sessions (2026); needs constitutional reform of Arts. 3 and 73 first. President Sheinbaum held forums on AI and minors (Aug–Sept 2026) feeding a separate initiative. | H5: Watch item
A6: Privacy / automated decisions | B6: Federal Law on Protection of Personal Data Held by Private Parties (new LFPDPPP, 2025) | C6: Binding statute | D6: Secretaría Anticorrupción y Buen Gobierno (replaced INAI) | E6: AI processing personal data, including automated decisions. | F6: Privacy notices, consent, ARCO rights; rights regarding automated processing that significantly affects the person (verify scope). | G6: New law published 20 Mar 2025; INAI dissolved and functions moved to the executive. | H6: All private-sector data controllers
A7: Employment | B7: Federal Labour Law — digital platform work reform (Art. 291-J and related) | C7: Binding statute | D7: Ministry of Labour (STPS) | E7: Algorithms that assign work, set pay or deactivate platform workers. | F7: Algorithmic transparency to workers: explain how automated systems assign tasks, evaluate and sanction. | G7: Platform-work reform in force 2025. | H7: Gig and delivery platforms
A8: Likeness / copyright | B8: Federal Copyright Law amendments (May 2026) | C8: Binding statute | D8: INDAUTOR; courts | E8: AI cloning or simulation of an artist's voice or image. | F8: Written consent required to clone or simulate a performer's voice or image with AI. | G8: Decree of 14 May 2026. | H8: Media, advertising, entertainment AI
A9: Consumer protection | B9: Federal Consumer Protection Law | C9: Binding statute | D9: PROFECO | E9: Misleading AI claims, chatbots in customer service, automated pricing. | F9: Truthful advertising; clear information to consumers. | G9: — | H9: Consumer-facing businesses
A10: Deepfakes | B10: State penal codes (e.g., 'Ley Olimpia' reforms) | C10: Binding statute (state level) | D10: State prosecutors | E10: Sexual deepfakes and digital violence. | F10: Criminal penalties for creating or sharing intimate content without consent, including AI-generated content in several states. | G10: — | H10: Platforms, image-generation tools

Sheet Brazil
A1: Brazil — AI Governance Laws
A2: Binding AI bill (PL 2338/2023) is stalled; AI is regulated today through LGPD, consumer law, children's online-safety law and electoral rules.
A4: Category | B4: Law / Instrument | C4: Type | D4: Regulator / Enforcer | E4: When it reaches AI | F4: Key obligations for organizations using AI | G4: 2025–26 developments & key dates | H4: Most affected
A5: Comprehensive AI law | B5: PL 2338/2023 — Brazilian AI Bill | C5: Pending bill | D5: Proposed: ANPD-coordinated national AI system (SIA) | E5: Would cover developers and deployers of AI, with high-risk categories. | F5: Proposed: risk classification, prohibited uses, algorithmic impact assessments, rights to explanation and human review, civil liability, copyright remuneration for training data. | G5: Passed Senate 10 Dec 2024; awaiting committee opinion in the Chamber of Deputies (as of Sept 2026). | H5: Watch item — all AI businesses
A6: Privacy / automated decisions | B6: LGPD — Lei 13.709/2018, Art. 20 | C6: Binding statute | D6: ANPD (now the National Data Protection Agency) | E6: Decisions made solely through automated processing that affect a person's interests (profiling, credit, employment). | F6: Right to request review of automated decisions; on request, clear information about criteria and procedures (subject to trade secrets); legal basis and DPIAs for high-risk processing. | G6: ANPD AI regulatory sandbox and consultations on AI and data protection (2025–26). | H6: All data controllers in Brazil
A7: Minors / platforms | B7: ECA Digital — Lei 15.211/2025 (Digital Statute of Children and Adolescents) | C7: Binding statute | D7: ANPD | E7: Digital services, including AI products and recommender systems, likely to be accessed by minors. | F7: Safety by default, age verification, parental controls, limits on profiling minors for ads, duty to prevent harmful content. | G7: Signed Sept 2025; in force March 2026. | H7: Platforms, apps, games, chatbots
A8: Elections / deepfakes | B8: TSE Resolution 23.755/2026 | C8: Binding electoral rule | D8: Superior Electoral Court (TSE) | E8: AI-generated campaign content and platforms during elections. | F8: Prominent AI labels on synthetic campaign content; total ban on electoral deepfakes; no new synthetic candidate content 72 hours before to 24 hours after voting; AI may not rank or recommend candidates; fines R$5,000–30,000, candidacy cancellation. | G8: Approved 2 Mar 2026; applies to the 4 Oct 2026 election and 25 Oct runoff. | H8: Campaigns, platforms, ad tech
A9: Consumer protection | B9: Consumer Defense Code (CDC) | C9: Binding statute | D9: Procon; Senacon; courts | E9: AI in consumer services, pricing, chatbots and credit. | F9: Information duties, ban on abusive practices, strict liability for defective services. | G9: — | H9: Consumer-facing businesses
A10: Platform liability | B10: Marco Civil da Internet, Art. 19 (STF ruling) | C10: Binding (court ruling) | D10: Supreme Federal Court | E10: Platforms hosting harmful content, including AI-generated content. | F10: Platforms may be liable after notice (and in some cases without a court order) for serious illegal content. | G10: Supreme Court ruling June 2025. | H10: Platforms
A11: Infrastructure | B11: Redata law (data-centre tax incentives) | C11: Binding statute | D11: Federal Revenue | E11: Data-centre equipment for AI. | F11: Suspends import duty and federal taxes on qualifying data-centre equipment. | G11: Signed 15 Sept 2026. | H11: Data-centre investors

Sheet India
A1: India — AI Governance Laws
A2: No AI-specific statute. India relies on the DPDP Act, IT Act rules (now covering AI-generated content), sector regulators and voluntary national AI guidelines.
A4: Category | B4: Law / Instrument | C4: Type | D4: Regulator / Enforcer | E4: When it reaches AI | F4: Key obligations for organizations using AI | G4: 2025–26 developments & key dates | H4: Most affected
A5: Comprehensive AI law | B5: India AI Governance Guidelines | C5: Voluntary guidelines | D5: MeitY | E5: All AI development and deployment. | F5: Seven principles ('sutras'): trust, people first, responsible innovation, fairness and equity, accountability, understandable by design, safety and resilience; six pillars and institutional proposals (AI governance group, AI Safety Institute). | G5: Released 5 Nov 2025; government explicitly chose not to propose an AI law for now. | H5: All — reference framework
A6: Privacy | B6: Digital Personal Data Protection Act 2023 & DPDP Rules 2025 | C6: Binding statute & rules | D6: Data Protection Board of India | E6: Any AI processing digital personal data of people in India, including training. | F6: Notice and consent (or legitimate use); purpose limitation; children's data needs verifiable parental consent and bans tracking and targeted ads; Significant Data Fiduciaries must run DPIAs, audits and algorithmic due-diligence checks; breach notification; penalties up to ₹250 crore per breach. | G6: Rules notified 13 Nov 2025; Board set up first; full obligations by 13 May 2027 (government considering acceleration). No explicit right against automated decisions. | H6: All businesses handling Indian personal data
A7: Synthetic content / platforms | B7: IT (Intermediary Guidelines and Digital Media Ethics Code) Amendment Rules 2026 | C7: Binding rules | D7: MeitY | E7: Synthetically generated information (AI-generated audio, image, video that appears real) on intermediaries. | F7: Prominent labels plus permanent metadata/provenance identifiers; no tools to strip labels; ban on prohibited synthetic content (CSAM, NCII, false documents, deceptive depictions); 3-hour takedown of unlawful content; large platforms (5M+ users) must verify user declarations and deploy detection. | G7: Notified 10 Feb 2026; in force 20 Feb 2026. | H7: Platforms, generative-AI services
A8: Financial services | B8: RBI FREE-AI Framework | C8: Regulator framework | D8: Reserve Bank of India | E8: AI used by banks, NBFCs and other regulated entities. | F8: Board-approved AI policy, model inventory, risk-based governance, bias and explainability checks, consumer disclosure, incident reporting. | G8: Released Aug 2025. | H8: Banks, NBFCs, fintechs
A9: Securities | B9: SEBI guidance on AI/ML in securities markets | C9: Regulator guidance | D9: SEBI | E9: AI used by brokers, advisers, exchanges and fund managers. | F9: Accountability for AI outputs, testing, data security, disclosure to clients where AI affects them. | G9: Consultation on responsible AI guidelines (June 2025) (verify final status). | H9: Brokers, AMCs, advisers
A10: Criminal / deepfakes | B10: IT Act 2000 & Bharatiya Nyaya Sanhita 2023 | C10: Binding statute | D10: Police; courts | E10: Deepfake impersonation, obscenity, defamation, cheating. | F10: Criminal liability for impersonation, publishing obscene or deceptive content; personality-rights injunctions granted by courts against AI misuse. | G10: Delhi and Bombay High Courts granting personality-rights orders against AI clones (2024–26). | H10: Platforms, content creators
A11: Copyright | B11: Copyright Act 1957 | C11: Binding statute | D11: Courts; DPIIT | E11: Training on copyrighted works. | F11: No TDM exception; training and outputs tested in court. | G11: ANI v. OpenAI pending in Delhi High Court; DPIIT working paper on AI and copyright (2025) (verify). | H11: Model developers, media
A12: Health | B12: ICMR Ethical Guidelines for AI in Biomedical Research and Healthcare | C12: Guidance | D12: ICMR | E12: AI in health research and care. | F12: Ethics review, consent, data safeguards, accountability. | G12: Issued 2023. | H12: Health-tech, hospitals

Sheet Gulf
A1: Gulf (GCC) — AI Governance Laws
A2: No GCC state has an enacted horizontal AI statute. Binding rules come from data-protection laws, free-zone regulations and — increasingly — central banks. Country is shown in the Category column.
A4: Category | B4: Law / Instrument | C4: Type | D4: Regulator / Enforcer | E4: When it reaches AI | F4: Key obligations for organizations using AI | G4: 2025–26 developments & key dates | H4: Most affected
A5: UAE · Privacy | B5: Federal Decree-Law 45/2021 (PDPL) | C5: Binding statute | D5: UAE Data Office (now within the new federal AI and data authority) | E5: AI processing personal data onshore in the UAE. | F5: Consent and lawful bases; right to object to automated processing producing legal effects; DPIAs for high-risk processing. | G5: Executive regulations long awaited (verify). | H5: All UAE businesses
A6: UAE · Automated systems (DIFC) | B6: DIFC Data Protection Regulation 10 (Autonomous & Semi-Autonomous Systems) | C6: Binding regulation | D6: DIFC Commissioner of Data Protection | E6: AI and autonomous systems processing personal data in the Dubai International Financial Centre. | F6: Notice of AI use and its purpose, human-defined principles, certification for high-risk processing, an autonomous-systems officer in some cases. | G6: In force Sept 2023; enforcement phasing from 2026 (verify). | H6: DIFC firms
A7: UAE · Financial | B7: CBUAE Guidance Note on AI/ML | C7: Supervisory guidance | D7: Central Bank of the UAE | E7: AI used by licensed financial institutions. | F7: Board accountability, model inventory, annual bias testing, human review, kill-switch capability. | G7: Issued Feb 2026. | H7: UAE banks, insurers, fintechs
A8: UAE · Governance | B8: UAE Charter for the Development and Use of AI; Federal Authority for AI and Data | C8: Principles; new regulator | D8: Federal Authority for AI and Data | E8: All AI. | F8: Non-binding principles: safety, privacy, bias avoidance, transparency, human oversight. | G8: Charter June 2024; new Cabinet-level authority June 2026 consolidating the AI Office and data functions. | H8: All
A9: Saudi Arabia · Privacy | B9: Personal Data Protection Law (PDPL) | C9: Binding statute | D9: SDAIA | E9: AI processing personal data of people in Saudi Arabia. | F9: Lawful basis, notice, data-subject rights, cross-border transfer limits, DPIAs; fines up to SAR 5M. | G9: Enforced since Sept 2024; 48 enforcement decisions by mid-2026. | H9: All KSA businesses
A10: Saudi Arabia · AI governance | B10: SDAIA AI Ethics Principles; Generative AI Guidelines; Deepfake Guidelines; National AI Risk Management Framework (SDAIA-P145) | C10: Guidance / national framework | D10: SDAIA | E10: All AI development and use. | F10: Ethics principles, GenAI risk controls, deepfake guidance; national methodology for identifying, assessing and monitoring AI risk. | G10: Risk framework issued July 2026. | H10: All
A11: Saudi Arabia · Copyright | B11: Copyright Law — text-and-data-mining exception | C11: Binding statute | D11: Saudi Authority for Intellectual Property | E11: Training AI on lawfully published works. | F11: Permits TDM within statutory limits. | G11: Effective 12 Aug 2026. | H11: Model developers
A12: Saudi Arabia · Pending | B12: Draft Global AI Hub Law | C12: Draft | D12: CST / SDAIA | E12: Foreign data and AI hosting. | F12: Proposed data 'embassy'-style hubs with home-country law applying. | G12: Consultation 2025; not enacted. | H12: Cloud and AI hosts
A13: Qatar · Financial | B13: Qatar Central Bank AI Guidelines | C13: Binding on licensed FIs | D13: Qatar Central Bank | E13: AI used by QCB-licensed institutions. | F13: AI strategy, risk assessments, approval gates for high-risk systems and before launching fully autonomous systems; customer disclosure. | G13: Issued Sept 2024. | H13: Qatari banks, insurers, fintechs
A14: Qatar · Privacy & ethics | B14: Personal Data Privacy Protection Law (Law 13/2016); MCIT Ethical AI Guidelines | C14: Binding statute; guidance | D14: National Cyber Governance and Assurance Affairs; MCIT | E14: AI processing personal data; all AI. | F14: Privacy safeguards, DPIAs for risky processing; ethical AI principles. | G14: MCIT guidelines 2025. | H14: All
A15: Bahrain · Pending AI law | B15: 38-article AI law proposal | C15: Pending | D15: — | E15: AI developers and users. | F15: Proposed licensing, prohibited uses and criminal penalties (up to 3 years' prison). | G15: Endorsed by Shura Council 2024; not enacted as of July 2026. Government AI policy mandatory for public bodies (May 2025). | H15: Watch item
A16: Oman · Policy | B16: National AI Policy; PDPL amendments | C16: Mandatory policy; pending amendments | D16: Ministry of Transport, Communications & IT | E16: AI in government and regulated use; automated processing of personal data. | F16: Governance standards, assessments, documentation and compliance reporting. | G16: Policy effective 9 Apr 2025; PDPL amendments on automated processing awaiting promulgation (May 2026). | H16: Government and vendors

Sheet Australia
A1: Australia — AI Governance Laws
A2: No standalone AI act. The National AI Plan (Dec 2025) relies on existing laws plus new privacy transparency rules, with an AI Safety Institute and Office of AI.
A4: Category | B4: Law / Instrument | C4: Type | D4: Regulator / Enforcer | E4: When it reaches AI | F4: Key obligations for organizations using AI | G4: 2025–26 developments & key dates | H4: Most affected
A5: Comprehensive AI law | B5: National AI Plan; Guidance for AI Adoption | C5: Policy; voluntary guidance | D5: Department of Industry; National AI Centre | E5: All AI. | F5: Guidance for AI Adoption (replaced the Voluntary AI Safety Standard, Oct 2025): governance, accountability, testing, transparency practices. | G5: National AI Plan Dec 2025 dropped the earlier proposal for mandatory guardrails on high-risk AI. AI Safety Institute established; Office of AI (July 2026) tasked with Australian AI standards (verify binding status). | H5: All
A6: Privacy / automated decisions | B6: Privacy Act 1988 as amended by Privacy and Other Legislation Amendment Act 2024 | C6: Binding statute | D6: OAIC | E6: Computer programs (including AI) that make, or substantially assist, decisions significantly affecting individuals' rights or interests. | F6: Privacy policies must disclose the kinds of personal information used and the kinds of decisions made by automated means. Australian Privacy Principles apply to AI training and use (OAIC guidance Oct 2024). | G6: Automated-decision transparency applies from 10 Dec 2026. Further 'tranche 2' reforms pending. | H6: APP entities using AI
A7: Privacy tort | B7: Statutory tort for serious invasions of privacy | C7: Binding statute | D7: Courts | E7: Serious privacy intrusions, including misuse of data or images by AI systems. | F7: Individuals can sue for serious, intentional or reckless invasions of privacy. | G7: In force 10 June 2025. | H7: All
A8: Deepfakes | B8: Criminal Code Amendment (Deepfake Sexual Material) Act 2024 | C8: Binding statute | D8: Federal police | E8: Creating or sharing non-consensual sexual deepfakes. | F8: Criminal offences with up to 6–7 years' imprisonment. | G8: In force 2024. | H8: Image-generation services, platforms
A9: Minors / online safety | B9: Online Safety Act 2021 & Social Media Minimum Age amendment | C9: Binding statute | D9: eSafety Commissioner | E9: Platforms, AI companions and generative services accessible to children. | F9: Under-16 social-media minimum age; industry codes covering AI companions and harmful AI-generated content. | G9: Minimum age in force 10 Dec 2025; new codes 2025–26. | H9: Platforms, chatbot providers
A10: Consumer protection | B10: Australian Consumer Law | C10: Binding statute | D10: ACCC | E10: Misleading AI claims, unfair practices, defective AI products. | F10: No misleading or deceptive conduct; consumer guarantees. | G10: ACCC reviewing AI and consumer law adequacy. | H10: Consumer-facing businesses
A11: Employment / discrimination | B11: Fair Work Act; federal anti-discrimination Acts | C11: Binding statute | D11: Fair Work Commission; AHRC | E11: AI in hiring, rostering, surveillance and dismissal. | F11: Liability for discriminatory outcomes; consultation duties on major workplace change. | G11: Parliamentary inquiry recommended treating workplace AI as high-risk (2025). | H11: Employers
A12: Financial services | B12: ASIC & APRA obligations (CPS 230) | C12: Binding regulation | D12: ASIC; APRA | E12: AI in financial services and operational risk. | F12: Operational-risk and third-party management; licensee obligations apply to AI use. | G12: CPS 230 in force July 2025; ASIC report on AI governance gaps (2024). | H12: Banks, insurers, super funds
A13: Copyright | B13: Copyright Act 1968 | C13: Binding statute | D13: Courts | E13: Training on copyrighted works. | F13: No TDM exception — permission needed. | G13: Government ruled out a TDM exception for AI training (Oct 2025). | H13: Model developers

Sheet Singapore
A1: Singapore — AI Governance Laws
A2: No AI act. Singapore leads on voluntary frameworks and testing tools, backed by the PDPA, sector rules (MAS) and targeted online-harm and election laws.
A4: Category | B4: Law / Instrument | C4: Type | D4: Regulator / Enforcer | E4: When it reaches AI | F4: Key obligations for organizations using AI | G4: 2025–26 developments & key dates | H4: Most affected
A5: Comprehensive AI law | B5: Model AI Governance Framework (2020), GenAI Framework (2024), Model AI Governance Framework for Agentic AI (2026) | C5: Voluntary | D5: IMDA; PDPC | E5: All AI, generative AI and AI agents. | F5: Internal governance, human involvement, operations management, stakeholder communication; for agents: bound risks, human accountability, technical controls, continuous monitoring. | G5: Agentic framework v1.0 launched 22 Jan 2026; v1.5 May 2026. AI Verify testing toolkit. | H5: All
A6: Privacy | B6: Personal Data Protection Act (PDPA) & Advisory Guidelines on AI Recommendation and Decision Systems | C6: Binding statute; guidance | D6: PDPC | E6: AI using personal data for development, recommendations or decisions. | F6: Consent or business-improvement/research exceptions; notification of AI use; accountability measures; fines up to 10% of Singapore turnover. | G6: AI guidelines issued Mar 2024. | H6: All organizations
A7: Financial services | B7: MAS FEAT principles; AI Risk Management Guidelines (proposed); Project MindForge toolkit | C7: Supervisory principles | D7: Monetary Authority of Singapore | E7: AI used by financial institutions. | F7: Fairness, ethics, accountability, transparency; AI inventory, risk materiality, lifecycle controls, board oversight. | G7: AIRG consulted Nov 2025–Jan 2026 (final status: verify); MindForge toolkit Mar 2026. | H7: Banks, insurers, fintechs
A8: Elections / deepfakes | B8: Elections (Integrity of Online Advertising) (Amendment) Act 2024 | C8: Binding statute | D8: Elections Department | E8: Deepfakes of election candidates. | F8: Ban on publishing realistic digitally manipulated content of candidates during election periods. | G8: Applied at the 2025 general election. | H8: Platforms, campaigns
A9: Online harms | B9: Online Safety (Relief and Accountability) Act 2025 | C9: Binding statute | D9: Online Safety Commission | E9: Online harms including intimate-image abuse and deepfakes. | F9: Victims can seek rapid takedown and redress; platform and user duties. | G9: Online Safety Commission operational from 2026 (verify). | H9: Platforms
A10: Employment | B10: Workplace Fairness Act 2025; Tripartite Guidelines on Fair Employment | C10: Binding statute | D10: Ministry of Manpower | E10: Discrimination in hiring and employment decisions, including AI-assisted ones. | F10: Prohibits discrimination on protected characteristics; grievance-handling processes. | G10: Act passed Jan 2025; commencement expected 2026–27 (verify). | H10: Employers
A11: Copyright | B11: Copyright Act 2021, s.244 (computational data analysis) | C11: Binding statute | D11: Courts | E11: Training AI on lawfully accessed works. | F11: Exception permits computational data analysis, including AI training, on lawfully accessed material. | G11: In force since 2021. | H11: Model developers
A12: Health | B12: AI in Healthcare Guidelines; Health Products Act (software medical devices) | C12: Guidance; binding regulation | D12: MOH; HSA | E12: AI in clinical care and medical-device software. | F12: Developer and implementer good practices; HSA registration for AI medical devices. | G12: — | H12: Health-tech, hospitals

Sheet Coverage Summary
A1: Coverage Summary — listed states with AI-specific law, by feature
A2: Live formulas count non-'—' cells in the State Matrix. Figures cover only the 26 states listed; a few entries are pending bills, studies or vetoes (NJ, VA, MA, FL) rather than enacted law.
A4: Feature (State Matrix column) | B4: States with an entry | C4: Share of listed states
A5: Consequential decisions / ADMT (comprehensive AI laws) | B5: =COUNTA('State Matrix'!$B$5:$B$30)-COUNTIF('State Matrix'!$B$5:$B$30,"—") -> 7 | C5: =IFERROR(B5/$B$15,0) -> 0.26923077
A6: Employment & hiring AI | B6: =COUNTA('State Matrix'!$C$5:$C$30)-COUNTIF('State Matrix'!$C$5:$C$30,"—") -> 8 | C6: =IFERROR(B6/$B$15,0) -> 0.30769231
A7: Privacy law — profiling & automated-decision rights | B7: =COUNTA('State Matrix'!$D$5:$D$30)-COUNTIF('State Matrix'!$D$5:$D$30,"—") -> 18 | C7: =IFERROR(B7/$B$15,0) -> 0.69230769
A8: Health care & insurance AI | B8: =COUNTA('State Matrix'!$E$5:$E$30)-COUNTIF('State Matrix'!$E$5:$E$30,"—") -> 11 | C8: =IFERROR(B8/$B$15,0) -> 0.42307692
A9: Chatbots, companions & minors | B9: =COUNTA('State Matrix'!$F$5:$F$30)-COUNTIF('State Matrix'!$F$5:$F$30,"—") -> 18 | C9: =IFERROR(B9/$B$15,0) -> 0.69230769
A10: Synthetic content, deepfakes & likeness | B10: =COUNTA('State Matrix'!$G$5:$G$30)-COUNTIF('State Matrix'!$G$5:$G$30,"—") -> 13 | C10: =IFERROR(B10/$B$15,0) -> 0.5
A11: Frontier model safety | B11: =COUNTA('State Matrix'!$H$5:$H$30)-COUNTIF('State Matrix'!$H$5:$H$30,"—") -> 5 | C11: =IFERROR(B11/$B$15,0) -> 0.19230769
A12: Biometrics, neural data & algorithmic pricing | B12: =COUNTA('State Matrix'!$I$5:$I$30)-COUNTIF('State Matrix'!$I$5:$I$30,"—") -> 10 | C12: =IFERROR(B12/$B$15,0) -> 0.38461538
A13: Government use · other · pending / key dates | B13: =COUNTA('State Matrix'!$J$5:$J$30)-COUNTIF('State Matrix'!$J$5:$J$30,"—") -> 14 | C13: =IFERROR(B13/$B$15,0) -> 0.53846154
A15: Total states listed | B15: =COUNTA('State Matrix'!$A$5:$A$30) -> 26
A17: Note: the last row (Government use · other · pending) is a catch-all, not a single regulated feature.
A19: Global Matrix — jurisdictions with an entry, by feature
A20: Feature (Global Matrix column) | B20: Jurisdictions with an entry | C20: Share of listed jurisdictions
A21: Comprehensive AI law / consequential decisions | B21: =COUNTA('Global Matrix'!$B$5:$B$16)-COUNTIF('Global Matrix'!$B$5:$B$16,"—") -> 12 | C21: =IFERROR(B21/$B$30,0) -> 1
A22: Employment & hiring AI | B22: =COUNTA('Global Matrix'!$C$5:$C$16)-COUNTIF('Global Matrix'!$C$5:$C$16,"—") -> 8 | C22: =IFERROR(B22/$B$30,0) -> 0.66666667
A23: Privacy law — automated-decision rights | B23: =COUNTA('Global Matrix'!$D$5:$D$16)-COUNTIF('Global Matrix'!$D$5:$D$16,"—") -> 12 | C23: =IFERROR(B23/$B$30,0) -> 1
A24: Health care & insurance AI | B24: =COUNTA('Global Matrix'!$E$5:$E$16)-COUNTIF('Global Matrix'!$E$5:$E$16,"—") -> 5 | C24: =IFERROR(B24/$B$30,0) -> 0.41666667
A25: Chatbots, companions & minors | B25: =COUNTA('Global Matrix'!$F$5:$F$16)-COUNTIF('Global Matrix'!$F$5:$F$16,"—") -> 7 | C25: =IFERROR(B25/$B$30,0) -> 0.58333333
A26: Synthetic content, deepfakes & likeness | B26: =COUNTA('Global Matrix'!$G$5:$G$16)-COUNTIF('Global Matrix'!$G$5:$G$16,"—") -> 10 | C26: =IFERROR(B26/$B$30,0) -> 0.83333333
A27: Frontier / general-purpose model rules | B27: =COUNTA('Global Matrix'!$H$5:$H$16)-COUNTIF('Global Matrix'!$H$5:$H$16,"—") -> 6 | C27: =IFERROR(B27/$B$30,0) -> 0.5
A28: Biometrics & surveillance | B28: =COUNTA('Global Matrix'!$I$5:$I$16)-COUNTIF('Global Matrix'!$I$5:$I$16,"—") -> 6 | C28: =IFERROR(B28/$B$30,0) -> 0.5
A29: Regulators · key dates · pending | B29: =COUNTA('Global Matrix'!$J$5:$J$16)-COUNTIF('Global Matrix'!$J$5:$J$16,"—") -> 12 | C29: =IFERROR(B29/$B$30,0) -> 1
A30: Total jurisdictions listed | B30: =COUNTA('Global Matrix'!$A$5:$A$16) -> 12
A32: Note: Global entries include voluntary frameworks and pending bills where no binding law exists — read the cell, not just the count.

Sheet Sources
A1: Sources
A2: Public reporting and law-firm analyses consulted for 2025–26 developments (accessed Sept–Oct 2026). Earlier laws reflect long-standing public record.
A4: Topic | B4: Source
A5: State AI law volume (84 laws, 27 states, H1 2026) | B5: Transparency Coalition mid-year report — https://www.transparencycoalition.ai/news/tcai-report-84-new-ai-laws-enacted-in-27-states-in-2026
A6: State legislation overview | B6: TechPolicy.Press — https://www.techpolicy.press/where-state-ai-legislation-stands-half-way-into-2026/
A7: Colorado SB 26-189 | B7: Crowell & Moring — https://www.crowell.com/en/insights/client-alerts/colorado-hits-reset-on-ai-regulation-sb-26-189-repeals-and-reenacts-the-colorado-ai-act
A8: Connecticut SB 5 | B8: Future of Privacy Forum — https://fpf.org/blog/sb-5-in-five-what-to-know-about-connecticuts-new-ai-law/
A9: Illinois SB 315 | B9: Crowell & Moring — https://www.crowell.com/en/insights/client-alerts/illinois-imposes-transparency-and-safety-obligations-on-frontier-ai-systems
A10: New York RAISE Act | B10: Wiley — https://www.wiley.law/alert-New-York-Finalizes-RAISE-Act-for-Frontier-AI-Models-Law-Takes-Effect-January-1-2027
A11: California 2026 session | B11: WilmerHale — https://www.wilmerhale.com/en/insights/blogs/wilmerhale-privacy-and-cybersecurity-law/20261002-california-finalizes-next-wave-of-state-ai-and-privacy-regulation
A12: California Adam's Law | B12: Office of Sen. Padilla — https://sd18.senate.ca.gov/news/governor-newsom-signs-adams-law
A13: Texas TRAIGA | B13: Promise Legal — https://blog.promise.legal/traiga-texas-ai-law-what-it-requires/
A14: Utah AI laws | B14: Ashurst Perkins Coie — https://www.ashurstperkinscoie.com/en/insights/new-utah-ai-laws-change-disclosure-requirements-and-identity-protections-target-mental-health-chatbo/
A15: Virginia SB 384 / HB 797 | B15: Fathom — https://fathom.org/insights/fathom-applauds-governor-spanberger-s-signing-of-landmark-ai-governance-legislation
... A38: Singapore | B38: Origin PI — https://originpi.com/blog/mas-ai-risk-management-2026/
